ks_bot_client/__init__.py
ks_bot_client/bot.py
ks_bot_client/ks_bot_exceptions.py
KS_BOT_Client_Python-2.5.1.dist-info/LICENSE
KS_BOT_Client_Python-2.5.1.dist-info/METADATA
KS_BOT_Client_Python-2.5.1.dist-info/WHEEL
KS_BOT_Client_Python-2.5.1.dist-info/top_level.txt
KS_BOT_Client_Python-2.5.1.dist-info/RECORD
