Metadata-Version: 2.1
Name: KS-BOT-Client-Python
Version: 2.5.1
Summary: Python framework for interacting with KS-BOT, without any app
Home-page: https://github.com/KidsSMIT/KS-BOT-Client-Python
Author: Kids SMIT
Author-email: codingwithcn@gmail.com
License: MIT
Project-URL: Bug Tracker, https://github.com/pypa/sampleproject/issues
Platform: UNKNOWN
Classifier: Programming Language :: Python :: 3
Classifier: License :: OSI Approved :: MIT License
Classifier: Operating System :: OS Independent
Requires-Python: >=3.6
Requires-Dist: python-socketio[client]
Requires-Dist: requests
